django_ajax/__init__.py
django_ajax/pagination.py
django_ajax/static/ajax-utilities/css/jquery.acomplete.css
django_ajax/static/ajax-utilities/css/jquery.mbox.css
django_ajax/static/ajax-utilities/css/tabbing.css
django_ajax/static/ajax-utilities/img/loader.gif
django_ajax/static/ajax-utilities/img/loader@2x.gif
django_ajax/static/ajax-utilities/img/jquery.mbox/b.png
django_ajax/static/ajax-utilities/img/jquery.mbox/bl.png
django_ajax/static/ajax-utilities/img/jquery.mbox/br.png
django_ajax/static/ajax-utilities/img/jquery.mbox/tl.png
django_ajax/static/ajax-utilities/img/jquery.mbox/tr.png
django_ajax/static/ajax-utilities/js/jquery.acomplete.js
django_ajax/static/ajax-utilities/js/jquery.mbox.js
django_ajax/static/ajax-utilities/js/pagination.js
django_ajax/static/ajax-utilities/js/tabbing.js
django_ajax/static/ajax-utilities/js/xhr.js
django_ajax/templates/django-ajax/_loader.html
django_ajax/templates/pagination/paginate-verbose.html
django_ajax/templates/pagination/paginate.html
django_ajax/templates/tabbing/default-style.html
django_ajax/templatetags/__init__.py
django_ajax/templatetags/pagination.py
django_ajax/templatetags/tabbing.py
django_ajax/templatetags/xhr.py
django_ajax_utilities-1.2.9.dist-info/DESCRIPTION.rst
django_ajax_utilities-1.2.9.dist-info/METADATA
django_ajax_utilities-1.2.9.dist-info/RECORD
django_ajax_utilities-1.2.9.dist-info/WHEEL
django_ajax_utilities-1.2.9.dist-info/metadata.json
django_ajax_utilities-1.2.9.dist-info/top_level.txt
