Metadata-Version: 2.0
Name: django-ajax-utilities
Version: 1.2.9
Summary: Pagination, xhr and tabbing utilities for the Django framework.
Home-page: https://github.com/vikingco/django-ajax-utilities
Author: Unleashed NV
Author-email: operations@unleashed.be
License: BSD
Platform: UNKNOWN
Classifier: Intended Audience :: Developers
Classifier: Programming Language :: Python
Classifier: Operating System :: OS Independent
Classifier: Environment :: Web Environment
Classifier: Framework :: Django
